{    
    "formal": [
        {
            "name": "Github",
            "link": "https://github.com/gauravghati/"
        },
        {
            "name": "Open Source Contributions",
            "link": "https://gauravghati.herokuapp.com/opensource/"
        },
        {
            "name": "Gmail",
            "link": "mailto:gurvghati@gmail.com"
        },
        {
            "name": "LinkedIn",
            "link": "http://linkedin.com/in/gauravghati/"
        },
        {
            "name": "Technical Blogs",
            "link": "https://gauravghati.herokuapp.com/blogs/"
        },
        {
            "name": "Github Stats",
            "link": "https://www.gitmemory.com/gauravghati"
        },
        {
            "name": "Codechef",
            "link": "https://www.codechef.com/users/gauravghati"
        }, 
        {
            "name": "HackerRank",
            "link": "https://www.hackerrank.com/gauravghati"
        },
        {
            "name": "Medium",
            "link": "https://medium.com/@gauravghati"
        }
    ],
 
    "informal": [
        {
            "name": "Good Sentences", 
            "link": "https://gauravghati.herokuapp.com/gist/goodsentences/"
        },
        {
            "name": "Good Reads", 
            "link": "https://www.goodreads.com/gauravghati"
        }
    ]
}
